llm_helpers/__init__.py
llm_helpers/generate_categories.py
llm_helpers-0.1.1.dist-info/LICENSE
llm_helpers-0.1.1.dist-info/METADATA
llm_helpers-0.1.1.dist-info/WHEEL
llm_helpers-0.1.1.dist-info/top_level.txt
llm_helpers-0.1.1.dist-info/RECORD
