Metadata-Version: 2.1
Name: llm_helpers
Version: 0.1.1
Summary: A helper package to work with LLMs
Home-page: https://github.com/sonnylaskar/llm_helpers
Author: Sonny Laskar
Author-email: sonnylaskar@gmail.com
Keywords: llm
Classifier: Programming Language :: Python :: 3
Classifier: Programming Language :: Python :: 3.9
Classifier: Programming Language :: Python :: 3.10
Classifier: Programming Language :: Python :: 3.11
Classifier: License :: OSI Approved :: Apache Software License
Classifier: Operating System :: OS Independent
Requires-Python: >=3.9
License-File: LICENSE
Requires-Dist: langchain-openai
Requires-Dist: langchain
